jk_rawhtml/CSSMap.py
jk_rawhtml/CSSStyleGroup.py
jk_rawhtml/Color.py
jk_rawhtml/ColorSpectrum.py
jk_rawhtml/HTML5HeadElement.py
jk_rawhtml/HTML5RootElement.py
jk_rawhtml/HTML5Scope.py
jk_rawhtml/HTMLComment.py
jk_rawhtml/HTMLElement.py
jk_rawhtml/HTMLRawCSS.py
jk_rawhtml/HTMLRawText.py
jk_rawhtml/HTMLStyleElement.py
jk_rawhtml/HTMLText.py
jk_rawhtml/_HTMLCSSProto.py
jk_rawhtml/_HTMLCommentProto.py
jk_rawhtml/_HTMLElementProto.py
jk_rawhtml/_HTMLRawCSSProto.py
jk_rawhtml/_HTMLRawTextProto.py
jk_rawhtml/_HTMLTextProto.py
jk_rawhtml/__init__.py
jk_rawhtml/htmlgeneral.py
jk_rawhtml/__OLD/Color.py
jk_rawhtml/__OLD/ColorSpectrum.py
jk_rawhtml-0.2026.1.20.dist-info/licenses/LICENSE.txt
jk_rawhtml-0.2026.1.20.dist-info/WHEEL
jk_rawhtml-0.2026.1.20.dist-info/METADATA
jk_rawhtml-0.2026.1.20.dist-info/RECORD
