Metadata-Version: 2.4
Name: jk_rawhtml
Version: 0.2026.1.20
Summary: This python module provides support for programmatically generating HTML5 code.
Keywords: html,css,html5
Author-email: Jürgen Knauth <pubsrc@binary-overflow.de>
Maintainer-email: Jürgen Knauth <pubsrc@binary-overflow.de>
Requires-Python: >=3.8
Classifier: Development Status :: 4 - Beta
Classifier: License :: OSI Approved :: Apache Software License
Classifier: Programming Language :: Python :: 3
License-File: LICENSE.txt
Requires-Dist: jk_hwriter >= 0.2026.1.20
Requires-Dist: jk_prettyprintobj
